<?xml version='1.0' encoding='utf-8'?>
<tv>
  <channel id="800">
    <display-name>NHK World</display-name>
    </channel>
  <programme start="20250624000000 +0800" stop="20250624003000 +0800" channel="800">
    <title>NHK NEWSLINE</title>
    </programme>
  <programme start="20250624003000 +0800" stop="20250624005700 +0800" channel="800">
    <title>Hometown Stories</title>
    </programme>
  <programme start="20250624005700 +0800" stop="20250624010000 +0800" channel="800">
    <title>Easy Japanese</title>
    </programme>
  <programme start="20250624010000 +0800" stop="20250624013000 +0800" channel="800">
    <title>NHK NEWSLINE</title>
    </programme>
  <programme start="20250624013000 +0800" stop="20250624014500 +0800" channel="800">
    <title>Activate Your Japanese!</title>
    </programme>
  <programme start="20250624014500 +0800" stop="20250624015500 +0800" channel="800">
    <title>Culture Crossroads</title>
    </programme>
  <programme start="20250624015500 +0800" stop="20250624020000 +0800" channel="800">
    <title>HELLO! NHK WORLD-JAPAN</title>
    </programme>
  <programme start="20250624020000 +0800" stop="20250624022800 +0800" channel="800">
    <title>NEWSROOM TOKYO</title>
    </programme>
  <programme start="20250624022800 +0800" stop="20250624024300 +0800" channel="800">
    <title>Direct Talk #101</title>
    </programme>
  <programme start="20250624024300 +0800" stop="20250624024800 +0800" channel="800">
    <title>One in Every Japanese</title>
    </programme>
  <programme start="20250624024800 +0800" stop="20250624025500 +0800" channel="800">
    <title>The Seasons of Yamato</title>
    </programme>
  <programme start="20250624025500 +0800" stop="20250624030000 +0800" channel="800">
    <title>Ukiyoe EDO-LIFE</title>
    </programme>
  <programme start="20250624030000 +0800" stop="20250624033000 +0800" channel="800">
    <title>Today's Close-Up</title>
    </programme>
  <programme start="20250624033000 +0800" stop="20250624040000 +0800" channel="800">
    <title>Seasoning the Seasons</title>
    </programme>
  <programme start="20250624040000 +0800" stop="20250624043000 +0800" channel="800">
    <title>NHK NEWSLINE&lt; NY &gt;</title>
    </programme>
  <programme start="20250624043000 +0800" stop="20250624050000 +0800" channel="800">
    <title>Medical Frontiers</title>
    </programme>
  <programme start="20250624050000 +0800" stop="20250624053000 +0800" channel="800">
    <title>NHK NEWSLINE&lt; NY &gt;</title>
    </programme>
  <programme start="20250624053000 +0800" stop="20250624060000 +0800" channel="800">
    <title>Where We Call Home</title>
    </programme>
  <programme start="20250624060000 +0800" stop="20250624063000 +0800" channel="800">
    <title>NHK NEWSLINE&lt; NY &gt;</title>
    </programme>
  <programme start="20250624063000 +0800" stop="20250624064500 +0800" channel="800">
    <title>Activate Your Japanese!</title>
    </programme>
  <programme start="20250624064500 +0800" stop="20250624065500 +0800" channel="800">
    <title>Culture Crossroads</title>
    </programme>
  <programme start="20250624065500 +0800" stop="20250624070000 +0800" channel="800">
    <title>HELLO! NHK WORLD-JAPAN</title>
    </programme>
  <programme start="20250624070000 +0800" stop="20250624073000 +0800" channel="800">
    <title>NHK NEWSLINE&lt; NY &gt;</title>
    </programme>
  <programme start="20250624073000 +0800" stop="20250624075700 +0800" channel="800">
    <title>Hometown Stories</title>
    </programme>
  <programme start="20250624075700 +0800" stop="20250624080000 +0800" channel="800">
    <title>Easy Japanese</title>
    </programme>
  <programme start="20250624080000 +0800" stop="20250624083000 +0800" channel="800">
    <title>NHK NEWSLINE&lt; NY &gt;</title>
    </programme>
  <programme start="20250624083000 +0800" stop="20250624090000 +0800" channel="800">
    <title>Journeys in Japan</title>
    </programme>
  <programme start="20250624090000 +0800" stop="20250624093000 +0800" channel="800">
    <title>NHK NEWSLINE&lt; NY &gt;</title>
    </programme>
  <programme start="20250624093000 +0800" stop="20250624100000 +0800" channel="800">
    <title>Dining with the Chef</title>
    </programme>
  <programme start="20250624100000 +0800" stop="20250624103000 +0800" channel="800">
    <title>NHK NEWSLINE</title>
    </programme>
  <programme start="20250624103000 +0800" stop="20250624110000 +0800" channel="800">
    <title>Document 72 hours</title>
    </programme>
  <programme start="20250624110000 +0800" stop="20250624113000 +0800" channel="800">
    <title>NHK NEWSLINE</title>
    </programme>
  <programme start="20250624113000 +0800" stop="20250624120000 +0800" channel="800">
    <title>Medical Frontiers</title>
    </programme>
  <programme start="20250624120000 +0800" stop="20250624123000 +0800" channel="800">
    <title>NHK NEWSLINE</title>
    </programme>
  <programme start="20250624123000 +0800" stop="20250624124500 +0800" channel="800">
    <title>DEEPER LOOK</title>
    </programme>
  <programme start="20250624124500 +0800" stop="20250624125500 +0800" channel="800">
    <title>Dig More Japan</title>
    </programme>
  <programme start="20250624125500 +0800" stop="20250624130000 +0800" channel="800">
    <title>Dining with the Chef Mini</title>
    </programme>
  <programme start="20250624130000 +0800" stop="20250624133000 +0800" channel="800">
    <title>NHK NEWSLINE</title>
    </programme>
  <programme start="20250624133000 +0800" stop="20250624140000 +0800" channel="800">
    <title>Journeys in Japan</title>
    </programme>
  <programme start="20250624140000 +0800" stop="20250624143000 +0800" channel="800">
    <title>NEWSLINE ASIA 24</title>
    </programme>
  <programme start="20250624143000 +0800" stop="20250624150000 +0800" channel="800">
    <title>Dining with the Chef</title>
    </programme>
  <programme start="20250624150000 +0800" stop="20250624153000 +0800" channel="800">
    <title>NEWSLINE ASIA 24</title>
    </programme>
  <programme start="20250624153000 +0800" stop="20250624160000 +0800" channel="800">
    <title>Document 72 hours</title>
    </programme>
  <programme start="20250624160000 +0800" stop="20250624163000 +0800" channel="800">
    <title>NHK NEWSLINE</title>
    </programme>
  <programme start="20250624163000 +0800" stop="20250624164500 +0800" channel="800">
    <title>DEEPER LOOK</title>
    </programme>
  <programme start="20250624164500 +0800" stop="20250624170000 +0800" channel="800">
    <title>BOSAI: Science that Can Save Your Life</title>
    </programme>
  <programme start="20250624170000 +0800" stop="20250624173000 +0800" channel="800">
    <title>NHK NEWSLINE</title>
    </programme>
  <programme start="20250624173000 +0800" stop="20250624180000 +0800" channel="800">
    <title>Medical Frontiers</title>
    </programme>
  <programme start="20250624180000 +0800" stop="20250624183000 +0800" channel="800">
    <title>NHK NEWS 7</title>
    </programme>
  <programme start="20250624183000 +0800" stop="20250624190000 +0800" channel="800">
    <title>Journeys in Japan</title>
    </programme>
  <programme start="20250624190000 +0800" stop="20250624192800 +0800" channel="800">
    <title>NEWSROOM TOKYO</title>
    </programme>
  <programme start="20250624192800 +0800" stop="20250624194300 +0800" channel="800">
    <title>Direct Talk #107</title>
    </programme>
  <programme start="20250624194300 +0800" stop="20250624194800 +0800" channel="800">
    <title>One in Every Japanese</title>
    </programme>
  <programme start="20250624194800 +0800" stop="20250624195500 +0800" channel="800">
    <title>The Beauty of Japanese Swords - Famous Masterpieces</title>
    </programme>
  <programme start="20250624195500 +0800" stop="20250624200000 +0800" channel="800">
    <title>Ukiyoe EDO-LIFE</title>
    </programme>
  <programme start="20250624200000 +0800" stop="20250624203000 +0800" channel="800">
    <title>NEWSROOM TOKYO</title>
    </programme>
  <programme start="20250624203000 +0800" stop="20250624210000 +0800" channel="800">
    <title>Dining with the Chef</title>
    </programme>
  <programme start="20250624210000 +0800" stop="20250624213000 +0800" channel="800">
    <title>NHK NEWSLINE</title>
    </programme>
  <programme start="20250624213000 +0800" stop="20250624220000 +0800" channel="800">
    <title>Document 72 hours</title>
    </programme>
  <programme start="20250624220000 +0800" stop="20250624223000 +0800" channel="800">
    <title>NHK NEWSLINE</title>
    </programme>
  <programme start="20250624223000 +0800" stop="20250624230000 +0800" channel="800">
    <title>Science View</title>
    </programme>
  <programme start="20250624230000 +0800" stop="20250624233000 +0800" channel="800">
    <title>NHK NEWSLINE</title>
    </programme>
  <programme start="20250624233000 +0800" stop="20250625000000 +0800" channel="800">
    <title>Journeys in Japan</title>
    </programme>
  <channel id="801">
    <display-name>CNA</display-name>
    </channel>
  <programme start="20250624000000 +0800" stop="20250624000300 +0800" channel="801">
    <title>Headline News</title>
    </programme>
  <programme start="20250624000300 +0800" stop="20250624010000 +0800" channel="801">
    <title>East Asia Tonight</title>
    </programme>
  <programme start="20250624010000 +0800" stop="20250624020000 +0800" channel="801">
    <title>Power To The People</title>
    </programme>
  <programme start="20250624020000 +0800" stop="20250624030000 +0800" channel="801">
    <title>Singapore Tonight</title>
    </programme>
  <programme start="20250624030000 +0800" stop="20250624040000 +0800" channel="801">
    <title>Insight</title>
    </programme>
  <programme start="20250624040000 +0800" stop="20250624050000 +0800" channel="801">
    <title>Asia Tonight</title>
    </programme>
  <programme start="20250624050000 +0800" stop="20250624060000 +0800" channel="801">
    <title>The Waves that Changed Us</title>
    </programme>
  <programme start="20250624060000 +0800" stop="20250624070000 +0800" channel="801">
    <title>Singapore Tonight</title>
    </programme>
  <programme start="20250624070000 +0800" stop="20250624100000 +0800" channel="801">
    <title>Asia First</title>
    </programme>
  <programme start="20250624100000 +0800" stop="20250624110000 +0800" channel="801">
    <title>The Waves that Changed Us</title>
    </programme>
  <programme start="20250624110000 +0800" stop="20250624130000 +0800" channel="801">
    <title>Asia Now</title>
    </programme>
  <programme start="20250624130000 +0800" stop="20250624140000 +0800" channel="801">
    <title>The Waves that Changed Us</title>
    </programme>
  <programme start="20250624140000 +0800" stop="20250624160000 +0800" channel="801">
    <title>Asia Now</title>
    </programme>
  <programme start="20250624160000 +0800" stop="20250624163000 +0800" channel="801">
    <title>In Search of Heat S2</title>
    </programme>
  <programme start="20250624163000 +0800" stop="20250624170000 +0800" channel="801">
    <title>CNA Correspondent</title>
    </programme>
  <programme start="20250624170000 +0800" stop="20250624170200 +0800" channel="801">
    <title>Headline News</title>
    </programme>
  <programme start="20250624170200 +0800" stop="20250624180000 +0800" channel="801">
    <title>Power To The People</title>
    </programme>
  <programme start="20250624180000 +0800" stop="20250624190000 +0800" channel="801">
    <title>East Asia Tonight</title>
    </programme>
  <programme start="20250624190000 +0800" stop="20250624200000 +0800" channel="801">
    <title>The Waves that Changed Us</title>
    </programme>
  <programme start="20250624200000 +0800" stop="20250624210000 +0800" channel="801">
    <title>Asia Tonight</title>
    </programme>
  <programme start="20250624210000 +0800" stop="20250624220000 +0800" channel="801">
    <title>The Waves that Changed Us</title>
    </programme>
  <programme start="20250624220000 +0800" stop="20250624230000 +0800" channel="801">
    <title>Singapore Tonight</title>
    </programme>
  <programme start="20250624230000 +0800" stop="20250625000000 +0800" channel="801">
    <title>The Waves that Changed Us</title>
    </programme>
  </tv>
